{"sha":"0477a802e2143debfa25109c45740ca56fb46870","node_id":"MDY6Q29tbWl0NjM2ODc5MDYyOjA0NzdhODAyZTIxNDNkZWJmYTI1MTA5YzQ1NzQwY2E1NmZiNDY4NzA=","commit":{"author":{"name":"Francesco Chicchiriccò","email":"ilgrosso@apache.org","date":"2020-11-18T14:52:51Z"},"committer":{"name":"Francesco Chicchiriccò","email":"ilgrosso@apache.org","date":"2020-11-18T14:52:51Z"},"message":"Upgrading Tomcat","tree":{"sha":"fc8e3c493ed2d9733add3039a1e4587a115a2bf5","url":"https://api.github.com/repos/EnricoDAlessandro97UNI/syncope/git/trees/fc8e3c493ed2d9733add3039a1e4587a115a2bf5"},"url":"https://api.github.com/repos/EnricoDAlessandro97UNI/syncope/git/commits/0477a802e2143debfa25109c45740ca56fb46870","comment_count":0,"verification":{"verified":false,"reason":"unsigned","signature":null,"payload":null}},"url":"https://api.github.com/repos/EnricoDAlessandro97UNI/syncope/commits/0477a802e2143debfa25109c45740ca56fb46870","html_url":"https://github.com/EnricoDAlessandro97UNI/syncope/commit/0477a802e2143debfa25109c45740ca56fb46870","comments_url":"https://api.github.com/repos/EnricoDAlessandro97UNI/syncope/commits/0477a802e2143debfa25109c45740ca56fb46870/comments","author":{"login":"ilgrosso","id":1064664,"node_id":"MDQ6VXNlcjEwNjQ2NjQ=","avatar_url":"https://avatars.githubusercontent.com/u/1064664?v=4","gravatar_id":"","url":"https://api.github.com/users/ilgrosso","html_url":"https://github.com/ilgrosso","followers_url":"https://api.github.com/users/ilgrosso/followers","following_url":"https://api.github.com/users/ilgrosso/following{/other_user}","gists_url":"https://api.github.com/users/ilgrosso/gists{/gist_id}","starred_url":"https://api.github.com/users/ilgrosso/starred{/owner}{/repo}","subscriptions_url":"https://api.github.com/users/ilgrosso/subscriptions","organizations_url":"https://api.github.com/users/ilgrosso/orgs","repos_url":"https://api.github.com/users/ilgrosso/repos","events_url":"https://api.github.com/users/ilgrosso/events{/privacy}","received_events_url":"https://api.github.com/users/ilgrosso/received_events","type":"User","site_admin":false},"committer":{"login":"ilgrosso","id":1064664,"node_id":"MDQ6VXNlcjEwNjQ2NjQ=","avatar_url":"https://avatars.githubusercontent.com/u/1064664?v=4","gravatar_id":"","url":"https://api.github.com/users/ilgrosso","html_url":"https://github.com/ilgrosso","followers_url":"https://api.github.com/users/ilgrosso/followers","following_url":"https://api.github.com/users/ilgrosso/following{/other_user}","gists_url":"https://api.github.com/users/ilgrosso/gists{/gist_id}","starred_url":"https://api.github.com/users/ilgrosso/starred{/owner}{/repo}","subscriptions_url":"https://api.github.com/users/ilgrosso/subscriptions","organizations_url":"https://api.github.com/users/ilgrosso/orgs","repos_url":"https://api.github.com/users/ilgrosso/repos","events_url":"https://api.github.com/users/ilgrosso/events{/privacy}","received_events_url":"https://api.github.com/users/ilgrosso/received_events","type":"User","site_admin":false},"parents":[{"sha":"021fdb0f16c720a688479c90330f6f27c8a4bf2a","url":"https://api.github.com/repos/EnricoDAlessandro97UNI/syncope/commits/021fdb0f16c720a688479c90330f6f27c8a4bf2a","html_url":"https://github.com/EnricoDAlessandro97UNI/syncope/commit/021fdb0f16c720a688479c90330f6f27c8a4bf2a"}],"stats":{"total":2,"additions":1,"deletions":1},"files":[{"sha":"282bc3905af42ae85884ab5c56cb461dbe99bae9","filename":"pom.xml","status":"modified","additions":1,"deletions":1,"changes":2,"blob_url":"https://github.com/EnricoDAlessandro97UNI/syncope/blob/0477a802e2143debfa25109c45740ca56fb46870/pom.xml","raw_url":"https://github.com/EnricoDAlessandro97UNI/syncope/raw/0477a802e2143debfa25109c45740ca56fb46870/pom.xml","contents_url":"https://api.github.com/repos/EnricoDAlessandro97UNI/syncope/contents/pom.xml?ref=0477a802e2143debfa25109c45740ca56fb46870","patch":"@@ -508,7 +508,7 @@ under the License.\n     <cargo.log>${log.directory}/cargo.log</cargo.log>\n     <cargo.output>${log.directory}/cargo-output.log</cargo.output>\n \n-    <tomcat.version>9.0.39</tomcat.version>\n+    <tomcat.version>9.0.40</tomcat.version>\n     <wildfly.version>21.0.0.Final</wildfly.version>\n     <payara.version>5.2020.6</payara.version>\n     <javax.faces.version>2.3.14</javax.faces.version>"}]}