{"sha":"1202f9c56f135c02d9d625b9b57464b50e8b1832","node_id":"MDY6Q29tbWl0NjM2ODc5MDYyOjEyMDJmOWM1NmYxMzVjMDJkOWQ2MjViOWI1NzQ2NGI1MGU4YjE4MzI=","commit":{"author":{"name":"Francesco Chicchiriccò","email":"ilgrosso@apache.org","date":"2016-06-24T08:03:07Z"},"committer":{"name":"Francesco Chicchiriccò","email":"ilgrosso@apache.org","date":"2016-06-24T08:03:07Z"},"message":"Updating CHANGES for release","tree":{"sha":"a3ae6f6933aa0c1d9633d0698c279282ab7a3ab7","url":"https://api.github.com/repos/EnricoDAlessandro97UNI/syncope/git/trees/a3ae6f6933aa0c1d9633d0698c279282ab7a3ab7"},"url":"https://api.github.com/repos/EnricoDAlessandro97UNI/syncope/git/commits/1202f9c56f135c02d9d625b9b57464b50e8b1832","comment_count":0,"verification":{"verified":false,"reason":"unsigned","signature":null,"payload":null}},"url":"https://api.github.com/repos/EnricoDAlessandro97UNI/syncope/commits/1202f9c56f135c02d9d625b9b57464b50e8b1832","html_url":"https://github.com/EnricoDAlessandro97UNI/syncope/commit/1202f9c56f135c02d9d625b9b57464b50e8b1832","comments_url":"https://api.github.com/repos/EnricoDAlessandro97UNI/syncope/commits/1202f9c56f135c02d9d625b9b57464b50e8b1832/comments","author":{"login":"ilgrosso","id":1064664,"node_id":"MDQ6VXNlcjEwNjQ2NjQ=","avatar_url":"https://avatars.githubusercontent.com/u/1064664?v=4","gravatar_id":"","url":"https://api.github.com/users/ilgrosso","html_url":"https://github.com/ilgrosso","followers_url":"https://api.github.com/users/ilgrosso/followers","following_url":"https://api.github.com/users/ilgrosso/following{/other_user}","gists_url":"https://api.github.com/users/ilgrosso/gists{/gist_id}","starred_url":"https://api.github.com/users/ilgrosso/starred{/owner}{/repo}","subscriptions_url":"https://api.github.com/users/ilgrosso/subscriptions","organizations_url":"https://api.github.com/users/ilgrosso/orgs","repos_url":"https://api.github.com/users/ilgrosso/repos","events_url":"https://api.github.com/users/ilgrosso/events{/privacy}","received_events_url":"https://api.github.com/users/ilgrosso/received_events","type":"User","site_admin":false},"committer":{"login":"ilgrosso","id":1064664,"node_id":"MDQ6VXNlcjEwNjQ2NjQ=","avatar_url":"https://avatars.githubusercontent.com/u/1064664?v=4","gravatar_id":"","url":"https://api.github.com/users/ilgrosso","html_url":"https://github.com/ilgrosso","followers_url":"https://api.github.com/users/ilgrosso/followers","following_url":"https://api.github.com/users/ilgrosso/following{/other_user}","gists_url":"https://api.github.com/users/ilgrosso/gists{/gist_id}","starred_url":"https://api.github.com/users/ilgrosso/starred{/owner}{/repo}","subscriptions_url":"https://api.github.com/users/ilgrosso/subscriptions","organizations_url":"https://api.github.com/users/ilgrosso/orgs","repos_url":"https://api.github.com/users/ilgrosso/repos","events_url":"https://api.github.com/users/ilgrosso/events{/privacy}","received_events_url":"https://api.github.com/users/ilgrosso/received_events","type":"User","site_admin":false},"parents":[{"sha":"72fd2cfc098b1e9c057d21e86e39af6175c0970b","url":"https://api.github.com/repos/EnricoDAlessandro97UNI/syncope/commits/72fd2cfc098b1e9c057d21e86e39af6175c0970b","html_url":"https://github.com/EnricoDAlessandro97UNI/syncope/commit/72fd2cfc098b1e9c057d21e86e39af6175c0970b"}],"stats":{"total":30,"additions":30,"deletions":0},"files":[{"sha":"bbaca1d028f206d3f01a35c08bd9107459e8953d","filename":"CHANGES","status":"modified","additions":30,"deletions":0,"changes":30,"blob_url":"https://github.com/EnricoDAlessandro97UNI/syncope/blob/1202f9c56f135c02d9d625b9b57464b50e8b1832/CHANGES","raw_url":"https://github.com/EnricoDAlessandro97UNI/syncope/raw/1202f9c56f135c02d9d625b9b57464b50e8b1832/CHANGES","contents_url":"https://api.github.com/repos/EnricoDAlessandro97UNI/syncope/contents/CHANGES?ref=1202f9c56f135c02d9d625b9b57464b50e8b1832","patch":"@@ -2,6 +2,36 @@ Apache Syncope - CHANGES\n Licensed under Apache License 2.0 - http://www.apache.org/licenses/LICENSE-2.0\n --------------------------------------------------------------------------------\n \n+Release Notes - Syncope - Version 2.0.0-M4\n+================================================================================\n+\n+** Bug\n+    * [SYNCOPE-845] - Type extensions not considered for user and any objects forms\n+    * [SYNCOPE-863] - Pull policy correlation rule plain attributes palette doesn't work fine\n+    * [SYNCOPE-865] - Random ConcurrentModificationException reported in the logs\n+    * [SYNCOPE-867] - Creating a new notification template the list of available templates are not updated after submit\n+    * [SYNCOPE-868] - Submit and cancel button not available in create report template modal page\n+    * [SYNCOPE-869] - Missing notification in case of success after create and update\n+    * [SYNCOPE-875] - Can't test LDAP Connector in admin console\n+    * [SYNCOPE-876] - Fake after object reported by propagation in case of delete\n+\n+** Improvement\n+    * [SYNCOPE-827] - Allow to specify user / group / any object filters for push tasks\n+    * [SYNCOPE-829] - Use actual pagination for resource explore\n+    * [SYNCOPE-852] - Add a good title including report/reportlet name modal used to edit report and reportlet\n+    * [SYNCOPE-862] - Membership and type extension improvements\n+    * [SYNCOPE-866] - Check for existence of key before adding template\n+    * [SYNCOPE-870] - Refer to users and groups by their names in Activiti workflow definition\n+    * [SYNCOPE-871] - Link NumberWidgets on the dashboard to their respective pages\n+    * [SYNCOPE-873] - Remove list() methods from User, Group and AnyObject REST APIs\n+\n+** New Feature\n+    * [SYNCOPE-721] - Enduser i18n\n+    * [SYNCOPE-859] - External Resource bulk operations\n+    * [SYNCOPE-860] - Allow listing group / role members\n+    * [SYNCOPE-864] - Support for Payara\n+    * [SYNCOPE-874] - Realm provisioning\n+\n Release Notes - Syncope - Version 2.0.0-M3\n ================================================================================\n "}]}