{"sha":"236d159da971c1f5380ec23de6582ea3d5ecddba","node_id":"MDY6Q29tbWl0NjM2ODc5MDYyOjIzNmQxNTlkYTk3MWMxZjUzODBlYzIzZGU2NTgyZWEzZDVlY2RkYmE=","commit":{"author":{"name":"Francesco Chicchiriccò","email":"ilgrosso@apache.org","date":"2020-03-27T13:34:59Z"},"committer":{"name":"Francesco Chicchiriccò","email":"ilgrosso@apache.org","date":"2020-03-27T13:34:59Z"},"message":"Quieting the install phase","tree":{"sha":"e2713bdfaaa31a96979194bb6c9718d63f47c822","url":"https://api.github.com/repos/EnricoDAlessandro97UNI/syncope/git/trees/e2713bdfaaa31a96979194bb6c9718d63f47c822"},"url":"https://api.github.com/repos/EnricoDAlessandro97UNI/syncope/git/commits/236d159da971c1f5380ec23de6582ea3d5ecddba","comment_count":0,"verification":{"verified":false,"reason":"unsigned","signature":null,"payload":null}},"url":"https://api.github.com/repos/EnricoDAlessandro97UNI/syncope/commits/236d159da971c1f5380ec23de6582ea3d5ecddba","html_url":"https://github.com/EnricoDAlessandro97UNI/syncope/commit/236d159da971c1f5380ec23de6582ea3d5ecddba","comments_url":"https://api.github.com/repos/EnricoDAlessandro97UNI/syncope/commits/236d159da971c1f5380ec23de6582ea3d5ecddba/comments","author":{"login":"ilgrosso","id":1064664,"node_id":"MDQ6VXNlcjEwNjQ2NjQ=","avatar_url":"https://avatars.githubusercontent.com/u/1064664?v=4","gravatar_id":"","url":"https://api.github.com/users/ilgrosso","html_url":"https://github.com/ilgrosso","followers_url":"https://api.github.com/users/ilgrosso/followers","following_url":"https://api.github.com/users/ilgrosso/following{/other_user}","gists_url":"https://api.github.com/users/ilgrosso/gists{/gist_id}","starred_url":"https://api.github.com/users/ilgrosso/starred{/owner}{/repo}","subscriptions_url":"https://api.github.com/users/ilgrosso/subscriptions","organizations_url":"https://api.github.com/users/ilgrosso/orgs","repos_url":"https://api.github.com/users/ilgrosso/repos","events_url":"https://api.github.com/users/ilgrosso/events{/privacy}","received_events_url":"https://api.github.com/users/ilgrosso/received_events","type":"User","site_admin":false},"committer":{"login":"ilgrosso","id":1064664,"node_id":"MDQ6VXNlcjEwNjQ2NjQ=","avatar_url":"https://avatars.githubusercontent.com/u/1064664?v=4","gravatar_id":"","url":"https://api.github.com/users/ilgrosso","html_url":"https://github.com/ilgrosso","followers_url":"https://api.github.com/users/ilgrosso/followers","following_url":"https://api.github.com/users/ilgrosso/following{/other_user}","gists_url":"https://api.github.com/users/ilgrosso/gists{/gist_id}","starred_url":"https://api.github.com/users/ilgrosso/starred{/owner}{/repo}","subscriptions_url":"https://api.github.com/users/ilgrosso/subscriptions","organizations_url":"https://api.github.com/users/ilgrosso/orgs","repos_url":"https://api.github.com/users/ilgrosso/repos","events_url":"https://api.github.com/users/ilgrosso/events{/privacy}","received_events_url":"https://api.github.com/users/ilgrosso/received_events","type":"User","site_admin":false},"parents":[{"sha":"e2b53adc0591eda3d9c4462df29edecb3d441bbf","url":"https://api.github.com/repos/EnricoDAlessandro97UNI/syncope/commits/e2b53adc0591eda3d9c4462df29edecb3d441bbf","html_url":"https://github.com/EnricoDAlessandro97UNI/syncope/commit/e2b53adc0591eda3d9c4462df29edecb3d441bbf"}],"stats":{"total":2,"additions":1,"deletions":1},"files":[{"sha":"d1bdc6345a6b82fb13b19d109cf5e9262922ad82","filename":".travis.yml","status":"modified","additions":1,"deletions":1,"changes":2,"blob_url":"https://github.com/EnricoDAlessandro97UNI/syncope/blob/236d159da971c1f5380ec23de6582ea3d5ecddba/.travis.yml","raw_url":"https://github.com/EnricoDAlessandro97UNI/syncope/raw/236d159da971c1f5380ec23de6582ea3d5ecddba/.travis.yml","contents_url":"https://api.github.com/repos/EnricoDAlessandro97UNI/syncope/contents/.travis.yml?ref=236d159da971c1f5380ec23de6582ea3d5ecddba","patch":"@@ -45,7 +45,7 @@ jobs:\n   include:\n     - stage: build\n       name: \"Build\"\n-      script: travis_wait 55 mvn -U -T 1C -P skipTests,all\n+      script: travis_wait 55 mvn -U --quiet -T 1C -P skipTests,all\n       #######################################################\n     - stage: validate\n       name: \"Checkstyle, Legal Files, Modernizer and Release Audit Tool (RAT) Analysis\""}]}