{"sha":"5ebfe4efbd71bd1d314b66d140ca901ae6cffb96","node_id":"MDY6Q29tbWl0NjM2ODc5MDYyOjVlYmZlNGVmYmQ3MWJkMWQzMTRiNjZkMTQwY2E5MDFhZTZjZmZiOTY=","commit":{"author":{"name":"Francesco Chicchiriccò","email":"ilgrosso@apache.org","date":"2021-08-16T12:49:50Z"},"committer":{"name":"Francesco Chicchiriccò","email":"ilgrosso@apache.org","date":"2021-08-16T12:49:50Z"},"message":"Upgrading greenmail and docker-maven-plugin","tree":{"sha":"c400a03f3be7d48367412727ed943baa07915377","url":"https://api.github.com/repos/EnricoDAlessandro97UNI/syncope/git/trees/c400a03f3be7d48367412727ed943baa07915377"},"url":"https://api.github.com/repos/EnricoDAlessandro97UNI/syncope/git/commits/5ebfe4efbd71bd1d314b66d140ca901ae6cffb96","comment_count":0,"verification":{"verified":false,"reason":"unsigned","signature":null,"payload":null}},"url":"https://api.github.com/repos/EnricoDAlessandro97UNI/syncope/commits/5ebfe4efbd71bd1d314b66d140ca901ae6cffb96","html_url":"https://github.com/EnricoDAlessandro97UNI/syncope/commit/5ebfe4efbd71bd1d314b66d140ca901ae6cffb96","comments_url":"https://api.github.com/repos/EnricoDAlessandro97UNI/syncope/commits/5ebfe4efbd71bd1d314b66d140ca901ae6cffb96/comments","author":{"login":"ilgrosso","id":1064664,"node_id":"MDQ6VXNlcjEwNjQ2NjQ=","avatar_url":"https://avatars.githubusercontent.com/u/1064664?v=4","gravatar_id":"","url":"https://api.github.com/users/ilgrosso","html_url":"https://github.com/ilgrosso","followers_url":"https://api.github.com/users/ilgrosso/followers","following_url":"https://api.github.com/users/ilgrosso/following{/other_user}","gists_url":"https://api.github.com/users/ilgrosso/gists{/gist_id}","starred_url":"https://api.github.com/users/ilgrosso/starred{/owner}{/repo}","subscriptions_url":"https://api.github.com/users/ilgrosso/subscriptions","organizations_url":"https://api.github.com/users/ilgrosso/orgs","repos_url":"https://api.github.com/users/ilgrosso/repos","events_url":"https://api.github.com/users/ilgrosso/events{/privacy}","received_events_url":"https://api.github.com/users/ilgrosso/received_events","type":"User","site_admin":false},"committer":{"login":"ilgrosso","id":1064664,"node_id":"MDQ6VXNlcjEwNjQ2NjQ=","avatar_url":"https://avatars.githubusercontent.com/u/1064664?v=4","gravatar_id":"","url":"https://api.github.com/users/ilgrosso","html_url":"https://github.com/ilgrosso","followers_url":"https://api.github.com/users/ilgrosso/followers","following_url":"https://api.github.com/users/ilgrosso/following{/other_user}","gists_url":"https://api.github.com/users/ilgrosso/gists{/gist_id}","starred_url":"https://api.github.com/users/ilgrosso/starred{/owner}{/repo}","subscriptions_url":"https://api.github.com/users/ilgrosso/subscriptions","organizations_url":"https://api.github.com/users/ilgrosso/orgs","repos_url":"https://api.github.com/users/ilgrosso/repos","events_url":"https://api.github.com/users/ilgrosso/events{/privacy}","received_events_url":"https://api.github.com/users/ilgrosso/received_events","type":"User","site_admin":false},"parents":[{"sha":"998d7efa37a6224bedd51f89441703c7691dac8e","url":"https://api.github.com/repos/EnricoDAlessandro97UNI/syncope/commits/998d7efa37a6224bedd51f89441703c7691dac8e","html_url":"https://github.com/EnricoDAlessandro97UNI/syncope/commit/998d7efa37a6224bedd51f89441703c7691dac8e"}],"stats":{"total":4,"additions":2,"deletions":2},"files":[{"sha":"968a0d83dd5e4821661ed027c6a3f2ffbb87c270","filename":"pom.xml","status":"modified","additions":2,"deletions":2,"changes":4,"blob_url":"https://github.com/EnricoDAlessandro97UNI/syncope/blob/5ebfe4efbd71bd1d314b66d140ca901ae6cffb96/pom.xml","raw_url":"https://github.com/EnricoDAlessandro97UNI/syncope/raw/5ebfe4efbd71bd1d314b66d140ca901ae6cffb96/pom.xml","contents_url":"https://api.github.com/repos/EnricoDAlessandro97UNI/syncope/contents/pom.xml?ref=5ebfe4efbd71bd1d314b66d140ca901ae6cffb96","patch":"@@ -1158,7 +1158,7 @@ under the License.\n       <dependency>\n         <groupId>com.icegreen</groupId>\n         <artifactId>greenmail</artifactId>\n-        <version>1.6.4</version>\n+        <version>1.6.5</version>\n         <exclusions>\n           <exclusion>\n             <groupId>junit</groupId>\n@@ -2247,7 +2247,7 @@ under the License.\n         <plugin>\n           <groupId>io.fabric8</groupId>\n           <artifactId>docker-maven-plugin</artifactId>\n-          <version>0.36.1</version>\n+          <version>0.37.0</version>\n         </plugin>\n \n         <plugin>"}]}