{"sha":"6b6b81ebd8fdb26525ee1b2359c0079498f00ef7","node_id":"MDY6Q29tbWl0NjM2ODc5MDYyOjZiNmI4MWViZDhmZGIyNjUyNWVlMWIyMzU5YzAwNzk0OThmMDBlZjc=","commit":{"author":{"name":"Francesco Chicchiriccò","email":"ilgrosso@apache.org","date":"2017-01-18T06:41:45Z"},"committer":{"name":"Francesco Chicchiriccò","email":"ilgrosso@apache.org","date":"2017-01-18T06:41:53Z"},"message":"Upgrading maven-compiler-plugin","tree":{"sha":"5cce0474b87b6174f609d8c32d7dcaec5aab8e34","url":"https://api.github.com/repos/EnricoDAlessandro97UNI/syncope/git/trees/5cce0474b87b6174f609d8c32d7dcaec5aab8e34"},"url":"https://api.github.com/repos/EnricoDAlessandro97UNI/syncope/git/commits/6b6b81ebd8fdb26525ee1b2359c0079498f00ef7","comment_count":0,"verification":{"verified":false,"reason":"unsigned","signature":null,"payload":null}},"url":"https://api.github.com/repos/EnricoDAlessandro97UNI/syncope/commits/6b6b81ebd8fdb26525ee1b2359c0079498f00ef7","html_url":"https://github.com/EnricoDAlessandro97UNI/syncope/commit/6b6b81ebd8fdb26525ee1b2359c0079498f00ef7","comments_url":"https://api.github.com/repos/EnricoDAlessandro97UNI/syncope/commits/6b6b81ebd8fdb26525ee1b2359c0079498f00ef7/comments","author":{"login":"ilgrosso","id":1064664,"node_id":"MDQ6VXNlcjEwNjQ2NjQ=","avatar_url":"https://avatars.githubusercontent.com/u/1064664?v=4","gravatar_id":"","url":"https://api.github.com/users/ilgrosso","html_url":"https://github.com/ilgrosso","followers_url":"https://api.github.com/users/ilgrosso/followers","following_url":"https://api.github.com/users/ilgrosso/following{/other_user}","gists_url":"https://api.github.com/users/ilgrosso/gists{/gist_id}","starred_url":"https://api.github.com/users/ilgrosso/starred{/owner}{/repo}","subscriptions_url":"https://api.github.com/users/ilgrosso/subscriptions","organizations_url":"https://api.github.com/users/ilgrosso/orgs","repos_url":"https://api.github.com/users/ilgrosso/repos","events_url":"https://api.github.com/users/ilgrosso/events{/privacy}","received_events_url":"https://api.github.com/users/ilgrosso/received_events","type":"User","site_admin":false},"committer":{"login":"ilgrosso","id":1064664,"node_id":"MDQ6VXNlcjEwNjQ2NjQ=","avatar_url":"https://avatars.githubusercontent.com/u/1064664?v=4","gravatar_id":"","url":"https://api.github.com/users/ilgrosso","html_url":"https://github.com/ilgrosso","followers_url":"https://api.github.com/users/ilgrosso/followers","following_url":"https://api.github.com/users/ilgrosso/following{/other_user}","gists_url":"https://api.github.com/users/ilgrosso/gists{/gist_id}","starred_url":"https://api.github.com/users/ilgrosso/starred{/owner}{/repo}","subscriptions_url":"https://api.github.com/users/ilgrosso/subscriptions","organizations_url":"https://api.github.com/users/ilgrosso/orgs","repos_url":"https://api.github.com/users/ilgrosso/repos","events_url":"https://api.github.com/users/ilgrosso/events{/privacy}","received_events_url":"https://api.github.com/users/ilgrosso/received_events","type":"User","site_admin":false},"parents":[{"sha":"fd998a2fc8abf5c013b12e9314fde198c1722d03","url":"https://api.github.com/repos/EnricoDAlessandro97UNI/syncope/commits/fd998a2fc8abf5c013b12e9314fde198c1722d03","html_url":"https://github.com/EnricoDAlessandro97UNI/syncope/commit/fd998a2fc8abf5c013b12e9314fde198c1722d03"}],"stats":{"total":2,"additions":1,"deletions":1},"files":[{"sha":"a25707a27b871022ab237f9cdba830032c0cd1aa","filename":"pom.xml","status":"modified","additions":1,"deletions":1,"changes":2,"blob_url":"https://github.com/EnricoDAlessandro97UNI/syncope/blob/6b6b81ebd8fdb26525ee1b2359c0079498f00ef7/pom.xml","raw_url":"https://github.com/EnricoDAlessandro97UNI/syncope/raw/6b6b81ebd8fdb26525ee1b2359c0079498f00ef7/pom.xml","contents_url":"https://api.github.com/repos/EnricoDAlessandro97UNI/syncope/contents/pom.xml?ref=6b6b81ebd8fdb26525ee1b2359c0079498f00ef7","patch":"@@ -1375,7 +1375,7 @@ under the License.\n         <plugin>\n           <groupId>org.apache.maven.plugins</groupId>\n           <artifactId>maven-compiler-plugin</artifactId>\n-          <version>3.6.0</version> \n+          <version>3.6.1</version> \n           <configuration>\n             <source>${targetJdk}</source>\n             <target>${targetJdk}</target>"}]}