{"sha":"70bc86225cae2148426f13d7cd341b6db9c7ec15","node_id":"MDY6Q29tbWl0NjM2ODc5MDYyOjcwYmM4NjIyNWNhZTIxNDg0MjZmMTNkN2NkMzQxYjZkYjljN2VjMTU=","commit":{"author":{"name":"Francesco Chicchiriccò","email":"ilgrosso@apache.org","date":"2020-05-07T06:27:29Z"},"committer":{"name":"Francesco Chicchiriccò","email":"ilgrosso@apache.org","date":"2020-05-07T06:27:29Z"},"message":"Upgrading Spring Security","tree":{"sha":"3192b8bf588663ed32ee775cf6db91a0c5e0afe7","url":"https://api.github.com/repos/EnricoDAlessandro97UNI/syncope/git/trees/3192b8bf588663ed32ee775cf6db91a0c5e0afe7"},"url":"https://api.github.com/repos/EnricoDAlessandro97UNI/syncope/git/commits/70bc86225cae2148426f13d7cd341b6db9c7ec15","comment_count":0,"verification":{"verified":false,"reason":"unsigned","signature":null,"payload":null}},"url":"https://api.github.com/repos/EnricoDAlessandro97UNI/syncope/commits/70bc86225cae2148426f13d7cd341b6db9c7ec15","html_url":"https://github.com/EnricoDAlessandro97UNI/syncope/commit/70bc86225cae2148426f13d7cd341b6db9c7ec15","comments_url":"https://api.github.com/repos/EnricoDAlessandro97UNI/syncope/commits/70bc86225cae2148426f13d7cd341b6db9c7ec15/comments","author":{"login":"ilgrosso","id":1064664,"node_id":"MDQ6VXNlcjEwNjQ2NjQ=","avatar_url":"https://avatars.githubusercontent.com/u/1064664?v=4","gravatar_id":"","url":"https://api.github.com/users/ilgrosso","html_url":"https://github.com/ilgrosso","followers_url":"https://api.github.com/users/ilgrosso/followers","following_url":"https://api.github.com/users/ilgrosso/following{/other_user}","gists_url":"https://api.github.com/users/ilgrosso/gists{/gist_id}","starred_url":"https://api.github.com/users/ilgrosso/starred{/owner}{/repo}","subscriptions_url":"https://api.github.com/users/ilgrosso/subscriptions","organizations_url":"https://api.github.com/users/ilgrosso/orgs","repos_url":"https://api.github.com/users/ilgrosso/repos","events_url":"https://api.github.com/users/ilgrosso/events{/privacy}","received_events_url":"https://api.github.com/users/ilgrosso/received_events","type":"User","site_admin":false},"committer":{"login":"ilgrosso","id":1064664,"node_id":"MDQ6VXNlcjEwNjQ2NjQ=","avatar_url":"https://avatars.githubusercontent.com/u/1064664?v=4","gravatar_id":"","url":"https://api.github.com/users/ilgrosso","html_url":"https://github.com/ilgrosso","followers_url":"https://api.github.com/users/ilgrosso/followers","following_url":"https://api.github.com/users/ilgrosso/following{/other_user}","gists_url":"https://api.github.com/users/ilgrosso/gists{/gist_id}","starred_url":"https://api.github.com/users/ilgrosso/starred{/owner}{/repo}","subscriptions_url":"https://api.github.com/users/ilgrosso/subscriptions","organizations_url":"https://api.github.com/users/ilgrosso/orgs","repos_url":"https://api.github.com/users/ilgrosso/repos","events_url":"https://api.github.com/users/ilgrosso/events{/privacy}","received_events_url":"https://api.github.com/users/ilgrosso/received_events","type":"User","site_admin":false},"parents":[{"sha":"472ec3e611a242ffa18cdb41cc94916049dee282","url":"https://api.github.com/repos/EnricoDAlessandro97UNI/syncope/commits/472ec3e611a242ffa18cdb41cc94916049dee282","html_url":"https://github.com/EnricoDAlessandro97UNI/syncope/commit/472ec3e611a242ffa18cdb41cc94916049dee282"}],"stats":{"total":2,"additions":1,"deletions":1},"files":[{"sha":"ab37ec47824842dc147ff8558662d5e6ee254077","filename":"pom.xml","status":"modified","additions":1,"deletions":1,"changes":2,"blob_url":"https://github.com/EnricoDAlessandro97UNI/syncope/blob/70bc86225cae2148426f13d7cd341b6db9c7ec15/pom.xml","raw_url":"https://github.com/EnricoDAlessandro97UNI/syncope/raw/70bc86225cae2148426f13d7cd341b6db9c7ec15/pom.xml","contents_url":"https://api.github.com/repos/EnricoDAlessandro97UNI/syncope/contents/pom.xml?ref=70bc86225cae2148426f13d7cd341b6db9c7ec15","patch":"@@ -409,7 +409,7 @@ under the License.\n     <jackson.version>2.11.0</jackson.version>\n \n     <spring.version>5.2.6.RELEASE</spring.version>\n-    <spring-security.version>5.3.1.RELEASE</spring-security.version>\n+    <spring-security.version>5.3.2.RELEASE</spring-security.version>\n     <spring-boot.version>2.2.6.RELEASE</spring-boot.version>\n     <spring-cloud-gateway.version>2.2.2.RELEASE</spring-cloud-gateway.version>\n "}]}