{"sha":"77730677654dbaa35442ca0d23d7abd2f0a2929d","node_id":"MDY6Q29tbWl0NjM2ODc5MDYyOjc3NzMwNjc3NjU0ZGJhYTM1NDQyY2EwZDIzZDdhYmQyZjBhMjkyOWQ=","commit":{"author":{"name":"Unknown","email":"unknown@apache.org","date":"2010-09-14T07:21:52Z"},"committer":{"name":"Unknown","email":"unknown@apache.org","date":"2010-09-14T07:21:52Z"},"message":"Preparing the first release (3)...\n\ngit-svn-id: https://svn.apache.org/repos/asf/incubator/syncope/trunk@1246477 13f79535-47bb-0310-9956-ffa450edef68","tree":{"sha":"34b5ddde2092722472165e6ed63705bd44ed97d7","url":"https://api.github.com/repos/EnricoDAlessandro97UNI/syncope/git/trees/34b5ddde2092722472165e6ed63705bd44ed97d7"},"url":"https://api.github.com/repos/EnricoDAlessandro97UNI/syncope/git/commits/77730677654dbaa35442ca0d23d7abd2f0a2929d","comment_count":0,"verification":{"verified":false,"reason":"unsigned","signature":null,"payload":null}},"url":"https://api.github.com/repos/EnricoDAlessandro97UNI/syncope/commits/77730677654dbaa35442ca0d23d7abd2f0a2929d","html_url":"https://github.com/EnricoDAlessandro97UNI/syncope/commit/77730677654dbaa35442ca0d23d7abd2f0a2929d","comments_url":"https://api.github.com/repos/EnricoDAlessandro97UNI/syncope/commits/77730677654dbaa35442ca0d23d7abd2f0a2929d/comments","author":null,"committer":null,"parents":[{"sha":"13f2f8764ab10e77b18eb463c5d35b9d9048f0b6","url":"https://api.github.com/repos/EnricoDAlessandro97UNI/syncope/commits/13f2f8764ab10e77b18eb463c5d35b9d9048f0b6","html_url":"https://github.com/EnricoDAlessandro97UNI/syncope/commit/13f2f8764ab10e77b18eb463c5d35b9d9048f0b6"}],"stats":{"total":32,"additions":16,"deletions":16},"files":[{"sha":"c6b0fa0f47841e9efe84bf9f3eae38e3327d1e00","filename":"core/pom.xml","status":"modified","additions":8,"deletions":8,"changes":16,"blob_url":"https://github.com/EnricoDAlessandro97UNI/syncope/blob/77730677654dbaa35442ca0d23d7abd2f0a2929d/core%2Fpom.xml","raw_url":"https://github.com/EnricoDAlessandro97UNI/syncope/raw/77730677654dbaa35442ca0d23d7abd2f0a2929d/core%2Fpom.xml","contents_url":"https://api.github.com/repos/EnricoDAlessandro97UNI/syncope/contents/core%2Fpom.xml?ref=77730677654dbaa35442ca0d23d7abd2f0a2929d","patch":"@@ -50,7 +50,7 @@\n         <dependency>\n             <groupId>org.syncope</groupId>\n             <artifactId>syncope-client</artifactId>\n-            <version>${parent.version}</version>\n+            <version>${project.version}</version>\n         </dependency>\n \n         <dependency>\n@@ -177,12 +177,12 @@\n         <dependency>\n             <groupId>org.syncope.identityconnectors</groupId>\n             <artifactId>framework</artifactId>\n-            <version>${parent.version}</version>\n+            <version>${project.version}</version>\n         </dependency>\n         <dependency>\n             <groupId>org.syncope.identityconnectors</groupId>\n             <artifactId>framework-internal</artifactId>\n-            <version>${parent.version}</version>\n+            <version>${project.version}</version>\n         </dependency>\n         <!-- /IdentityConnectors -->\n \n@@ -199,7 +199,7 @@\n         <dependency>\n             <groupId>org.syncope.identityconnectors.bundles.staticws</groupId>\n             <artifactId>staticwebservice</artifactId>\n-            <version>${parent.version}</version>\n+            <version>${project.version}</version>\n             <scope>test</scope>\n         </dependency>\n         <dependency>\n@@ -221,13 +221,13 @@\n         <dependency>\n             <groupId>org.syncope.identityconnectors</groupId>\n             <artifactId>test-common</artifactId>\n-            <version>${parent.version}</version>\n+            <version>${project.version}</version>\n             <scope>test</scope>\n         </dependency>\n         <dependency>\n             <groupId>org.syncope.identityconnectors.bundles.staticws</groupId>\n             <artifactId>ws-target-resource</artifactId>\n-            <version>${parent.version}</version>\n+            <version>${project.version}</version>\n             <type>war</type>\n             <scope>test</scope>\n         </dependency>\n@@ -405,7 +405,7 @@\n                                 <artifactItem>\n                                     <groupId>org.syncope.identityconnectors.bundles.staticws</groupId>\n                                     <artifactId>staticwebservice</artifactId>\n-                                    <version>${parent.version}</version>\n+                                    <version>${project.version}</version>\n                                     <outputDirectory>/tmp/bundles</outputDirectory>\n                                 </artifactItem>\n                             </artifactItems>\n@@ -476,7 +476,7 @@\n                 <configuration>\n                     <stopKey>foo</stopKey>\n                     <stopPort>9999</stopPort>\n-                    <webApp>${settings.localRepository}/org/syncope/identityconnectors/bundles/staticws/ws-target-resource/${parent.version}/ws-target-resource-${parent.version}.war</webApp>\n+                    <webApp>${settings.localRepository}/org/syncope/identityconnectors/bundles/staticws/ws-target-resource/${project.version}/ws-target-resource-${project.version}.war</webApp>\n                     <contextPath>wstarget</contextPath>\n                     <connectors>\n                         <connector implementation=\"org.mortbay.jetty.nio.SelectChannelConnector\">"},{"sha":"9a95fc17e2f30ef356fa24a4f2ca4b0b3869de0e","filename":"identityconnectors/bundles/staticws/staticwebservice/pom.xml","status":"modified","additions":5,"deletions":5,"changes":10,"blob_url":"https://github.com/EnricoDAlessandro97UNI/syncope/blob/77730677654dbaa35442ca0d23d7abd2f0a2929d/identityconnectors%2Fbundles%2Fstaticws%2Fstaticwebservice%2Fpom.xml","raw_url":"https://github.com/EnricoDAlessandro97UNI/syncope/raw/77730677654dbaa35442ca0d23d7abd2f0a2929d/identityconnectors%2Fbundles%2Fstaticws%2Fstaticwebservice%2Fpom.xml","contents_url":"https://api.github.com/repos/EnricoDAlessandro97UNI/syncope/contents/identityconnectors%2Fbundles%2Fstaticws%2Fstaticwebservice%2Fpom.xml?ref=77730677654dbaa35442ca0d23d7abd2f0a2929d","patch":"@@ -69,14 +69,14 @@\n         <dependency>\n             <groupId>org.syncope.identityconnectors</groupId>\n             <artifactId>framework</artifactId>\n-            <version>${parent.version}</version>\n+            <version>${project.version}</version>\n             <scope>compile</scope>\n         </dependency>\n \n         <dependency>\n             <groupId>org.syncope.identityconnectors</groupId>\n             <artifactId>framework-internal</artifactId>\n-            <version>${parent.version}</version>\n+            <version>${project.version}</version>\n             <scope>runtime</scope>\n         </dependency>\n \n@@ -92,7 +92,7 @@\n         <dependency>\n             <groupId>org.syncope.identityconnectors.bundles.staticws</groupId>\n             <artifactId>utilities</artifactId>\n-            <version>${parent.version}</version>\n+            <version>${project.version}</version>\n         </dependency>\n \n         <!-- TEST -->\n@@ -106,15 +106,15 @@\n         <dependency>\n             <groupId>org.syncope.identityconnectors</groupId>\n             <artifactId>test-common</artifactId>\n-            <version>${parent.version}</version>\n+            <version>${project.version}</version>\n             <scope>test</scope>\n         </dependency>\n \n         <dependency>\n             <groupId>org.syncope.identityconnectors.bundles.staticws</groupId>\n             <artifactId>ws-target-resource</artifactId>\n             <type>war</type>\n-            <version>${parent.version}</version>\n+            <version>${project.version}</version>\n             <scope>runtime</scope>\n         </dependency>\n "},{"sha":"7e6625a07e6dd30a22445b8a4530ea711f47e299","filename":"identityconnectors/framework-internal/pom.xml","status":"modified","additions":2,"deletions":2,"changes":4,"blob_url":"https://github.com/EnricoDAlessandro97UNI/syncope/blob/77730677654dbaa35442ca0d23d7abd2f0a2929d/identityconnectors%2Fframework-internal%2Fpom.xml","raw_url":"https://github.com/EnricoDAlessandro97UNI/syncope/raw/77730677654dbaa35442ca0d23d7abd2f0a2929d/identityconnectors%2Fframework-internal%2Fpom.xml","contents_url":"https://api.github.com/repos/EnricoDAlessandro97UNI/syncope/contents/identityconnectors%2Fframework-internal%2Fpom.xml?ref=77730677654dbaa35442ca0d23d7abd2f0a2929d","patch":"@@ -20,14 +20,14 @@\n         <dependency>\n             <groupId>org.syncope.identityconnectors</groupId>\n             <artifactId>framework</artifactId>\n-            <version>${parent.version}</version>\n+            <version>${project.version}</version>\n             <scope>provided</scope>\n         </dependency>\n \n         <dependency>\n             <groupId>org.syncope.identityconnectors</groupId>\n             <artifactId>test-common</artifactId>\n-            <version>${parent.version}</version>\n+            <version>${project.version}</version>\n             <scope>provided</scope>\n         </dependency>\n "},{"sha":"0631a6b9711d3feb318a4ba98cf42104a5c0eb0a","filename":"identityconnectors/test-common/pom.xml","status":"modified","additions":1,"deletions":1,"changes":2,"blob_url":"https://github.com/EnricoDAlessandro97UNI/syncope/blob/77730677654dbaa35442ca0d23d7abd2f0a2929d/identityconnectors%2Ftest-common%2Fpom.xml","raw_url":"https://github.com/EnricoDAlessandro97UNI/syncope/raw/77730677654dbaa35442ca0d23d7abd2f0a2929d/identityconnectors%2Ftest-common%2Fpom.xml","contents_url":"https://api.github.com/repos/EnricoDAlessandro97UNI/syncope/contents/identityconnectors%2Ftest-common%2Fpom.xml?ref=77730677654dbaa35442ca0d23d7abd2f0a2929d","patch":"@@ -20,7 +20,7 @@\n             <groupId>org.syncope.identityconnectors</groupId>\n             <artifactId>framework</artifactId>\n             <scope>compile</scope>\n-            <version>${parent.version}</version>\n+            <version>${project.version}</version>\n         </dependency>\n \n         <dependency>"}]}