{"sha":"7a9d868f2c3353697efe1808821e1ba5283c352a","node_id":"MDY6Q29tbWl0NjM2ODc5MDYyOjdhOWQ4NjhmMmMzMzUzNjk3ZWZlMTgwODgyMWUxYmE1MjgzYzM1MmE=","commit":{"author":{"name":"Francesco Chicchiriccò","email":"ilgrosso@apache.org","date":"2019-12-02T07:07:28Z"},"committer":{"name":"Francesco Chicchiriccò","email":"ilgrosso@apache.org","date":"2019-12-02T07:08:24Z"},"message":"Upgrading Mockito, checkstyle and cargo-maven2-plugin","tree":{"sha":"4f4ca20f7c5462919c8ce62fbf19d3609ba97d41","url":"https://api.github.com/repos/EnricoDAlessandro97UNI/syncope/git/trees/4f4ca20f7c5462919c8ce62fbf19d3609ba97d41"},"url":"https://api.github.com/repos/EnricoDAlessandro97UNI/syncope/git/commits/7a9d868f2c3353697efe1808821e1ba5283c352a","comment_count":0,"verification":{"verified":false,"reason":"unsigned","signature":null,"payload":null}},"url":"https://api.github.com/repos/EnricoDAlessandro97UNI/syncope/commits/7a9d868f2c3353697efe1808821e1ba5283c352a","html_url":"https://github.com/EnricoDAlessandro97UNI/syncope/commit/7a9d868f2c3353697efe1808821e1ba5283c352a","comments_url":"https://api.github.com/repos/EnricoDAlessandro97UNI/syncope/commits/7a9d868f2c3353697efe1808821e1ba5283c352a/comments","author":{"login":"ilgrosso","id":1064664,"node_id":"MDQ6VXNlcjEwNjQ2NjQ=","avatar_url":"https://avatars.githubusercontent.com/u/1064664?v=4","gravatar_id":"","url":"https://api.github.com/users/ilgrosso","html_url":"https://github.com/ilgrosso","followers_url":"https://api.github.com/users/ilgrosso/followers","following_url":"https://api.github.com/users/ilgrosso/following{/other_user}","gists_url":"https://api.github.com/users/ilgrosso/gists{/gist_id}","starred_url":"https://api.github.com/users/ilgrosso/starred{/owner}{/repo}","subscriptions_url":"https://api.github.com/users/ilgrosso/subscriptions","organizations_url":"https://api.github.com/users/ilgrosso/orgs","repos_url":"https://api.github.com/users/ilgrosso/repos","events_url":"https://api.github.com/users/ilgrosso/events{/privacy}","received_events_url":"https://api.github.com/users/ilgrosso/received_events","type":"User","site_admin":false},"committer":{"login":"ilgrosso","id":1064664,"node_id":"MDQ6VXNlcjEwNjQ2NjQ=","avatar_url":"https://avatars.githubusercontent.com/u/1064664?v=4","gravatar_id":"","url":"https://api.github.com/users/ilgrosso","html_url":"https://github.com/ilgrosso","followers_url":"https://api.github.com/users/ilgrosso/followers","following_url":"https://api.github.com/users/ilgrosso/following{/other_user}","gists_url":"https://api.github.com/users/ilgrosso/gists{/gist_id}","starred_url":"https://api.github.com/users/ilgrosso/starred{/owner}{/repo}","subscriptions_url":"https://api.github.com/users/ilgrosso/subscriptions","organizations_url":"https://api.github.com/users/ilgrosso/orgs","repos_url":"https://api.github.com/users/ilgrosso/repos","events_url":"https://api.github.com/users/ilgrosso/events{/privacy}","received_events_url":"https://api.github.com/users/ilgrosso/received_events","type":"User","site_admin":false},"parents":[{"sha":"5c6c6d22847ec2c95169632ff8138f5749cdf34a","url":"https://api.github.com/repos/EnricoDAlessandro97UNI/syncope/commits/5c6c6d22847ec2c95169632ff8138f5749cdf34a","html_url":"https://github.com/EnricoDAlessandro97UNI/syncope/commit/5c6c6d22847ec2c95169632ff8138f5749cdf34a"}],"stats":{"total":6,"additions":3,"deletions":3},"files":[{"sha":"2400a92b58359b17c8cdc17babbcd40bce9c0a66","filename":"pom.xml","status":"modified","additions":3,"deletions":3,"changes":6,"blob_url":"https://github.com/EnricoDAlessandro97UNI/syncope/blob/7a9d868f2c3353697efe1808821e1ba5283c352a/pom.xml","raw_url":"https://github.com/EnricoDAlessandro97UNI/syncope/raw/7a9d868f2c3353697efe1808821e1ba5283c352a/pom.xml","contents_url":"https://api.github.com/repos/EnricoDAlessandro97UNI/syncope/contents/pom.xml?ref=7a9d868f2c3353697efe1808821e1ba5283c352a","patch":"@@ -1795,7 +1795,7 @@ under the License.\n       <dependency>\n         <groupId>org.mockito</groupId>\n         <artifactId>mockito-core</artifactId>\n-        <version>3.1.0</version>\n+        <version>3.2.0</version>\n         <scope>test</scope>\n       </dependency>\n       <dependency>\n@@ -2035,7 +2035,7 @@ under the License.\n         <plugin>\n           <groupId>org.codehaus.cargo</groupId>\n           <artifactId>cargo-maven2-plugin</artifactId>\n-          <version>1.7.7</version>\n+          <version>1.7.8</version>\n           <configuration>\n             <configuration>\n               <type>standalone</type>\n@@ -2087,7 +2087,7 @@ under the License.\n             <dependency>\n               <groupId>com.puppycrawl.tools</groupId>\n               <artifactId>checkstyle</artifactId>\n-              <version>8.26</version>\n+              <version>8.27</version>\n             </dependency>\n           </dependencies>\n           <configuration>"}]}