{"sha":"ae51fbe1ef8dd658a0ffea25082d5419fc21fd64","node_id":"MDY6Q29tbWl0NjM2ODc5MDYyOmFlNTFmYmUxZWY4ZGQ2NThhMGZmZWEyNTA4MmQ1NDE5ZmMyMWZkNjQ=","commit":{"author":{"name":"Francesco Chicchiriccò","email":"ilgrosso@apache.org","date":"2019-10-18T06:24:03Z"},"committer":{"name":"Francesco Chicchiriccò","email":"ilgrosso@apache.org","date":"2019-10-18T06:24:26Z"},"message":"Upgrading Swagger UI and modernizer-maven-plugin","tree":{"sha":"fe068de0499a5844f2c84235a4615f29cbb9efd1","url":"https://api.github.com/repos/EnricoDAlessandro97UNI/syncope/git/trees/fe068de0499a5844f2c84235a4615f29cbb9efd1"},"url":"https://api.github.com/repos/EnricoDAlessandro97UNI/syncope/git/commits/ae51fbe1ef8dd658a0ffea25082d5419fc21fd64","comment_count":0,"verification":{"verified":false,"reason":"unsigned","signature":null,"payload":null}},"url":"https://api.github.com/repos/EnricoDAlessandro97UNI/syncope/commits/ae51fbe1ef8dd658a0ffea25082d5419fc21fd64","html_url":"https://github.com/EnricoDAlessandro97UNI/syncope/commit/ae51fbe1ef8dd658a0ffea25082d5419fc21fd64","comments_url":"https://api.github.com/repos/EnricoDAlessandro97UNI/syncope/commits/ae51fbe1ef8dd658a0ffea25082d5419fc21fd64/comments","author":{"login":"ilgrosso","id":1064664,"node_id":"MDQ6VXNlcjEwNjQ2NjQ=","avatar_url":"https://avatars.githubusercontent.com/u/1064664?v=4","gravatar_id":"","url":"https://api.github.com/users/ilgrosso","html_url":"https://github.com/ilgrosso","followers_url":"https://api.github.com/users/ilgrosso/followers","following_url":"https://api.github.com/users/ilgrosso/following{/other_user}","gists_url":"https://api.github.com/users/ilgrosso/gists{/gist_id}","starred_url":"https://api.github.com/users/ilgrosso/starred{/owner}{/repo}","subscriptions_url":"https://api.github.com/users/ilgrosso/subscriptions","organizations_url":"https://api.github.com/users/ilgrosso/orgs","repos_url":"https://api.github.com/users/ilgrosso/repos","events_url":"https://api.github.com/users/ilgrosso/events{/privacy}","received_events_url":"https://api.github.com/users/ilgrosso/received_events","type":"User","site_admin":false},"committer":{"login":"ilgrosso","id":1064664,"node_id":"MDQ6VXNlcjEwNjQ2NjQ=","avatar_url":"https://avatars.githubusercontent.com/u/1064664?v=4","gravatar_id":"","url":"https://api.github.com/users/ilgrosso","html_url":"https://github.com/ilgrosso","followers_url":"https://api.github.com/users/ilgrosso/followers","following_url":"https://api.github.com/users/ilgrosso/following{/other_user}","gists_url":"https://api.github.com/users/ilgrosso/gists{/gist_id}","starred_url":"https://api.github.com/users/ilgrosso/starred{/owner}{/repo}","subscriptions_url":"https://api.github.com/users/ilgrosso/subscriptions","organizations_url":"https://api.github.com/users/ilgrosso/orgs","repos_url":"https://api.github.com/users/ilgrosso/repos","events_url":"https://api.github.com/users/ilgrosso/events{/privacy}","received_events_url":"https://api.github.com/users/ilgrosso/received_events","type":"User","site_admin":false},"parents":[{"sha":"08a534d6464d78dbc24a9dd58dd04ecfcddb11a9","url":"https://api.github.com/repos/EnricoDAlessandro97UNI/syncope/commits/08a534d6464d78dbc24a9dd58dd04ecfcddb11a9","html_url":"https://github.com/EnricoDAlessandro97UNI/syncope/commit/08a534d6464d78dbc24a9dd58dd04ecfcddb11a9"}],"stats":{"total":4,"additions":2,"deletions":2},"files":[{"sha":"aa5785dac2ada91b8b7c542519a0ee4c0ef55716","filename":"pom.xml","status":"modified","additions":2,"deletions":2,"changes":4,"blob_url":"https://github.com/EnricoDAlessandro97UNI/syncope/blob/ae51fbe1ef8dd658a0ffea25082d5419fc21fd64/pom.xml","raw_url":"https://github.com/EnricoDAlessandro97UNI/syncope/raw/ae51fbe1ef8dd658a0ffea25082d5419fc21fd64/pom.xml","contents_url":"https://api.github.com/repos/EnricoDAlessandro97UNI/syncope/contents/pom.xml?ref=ae51fbe1ef8dd658a0ffea25082d5419fc21fd64","patch":"@@ -454,7 +454,7 @@ under the License.\n     <log.directory>${project.build.directory}/log</log.directory>\n \n     <swagger-core.version>2.0.10</swagger-core.version>    \n-    <swagger-ui.version>3.23.8</swagger-ui.version>\n+    <swagger-ui.version>3.24.0</swagger-ui.version>\n     <guava.version>20.0</guava.version>\n \n     <jquery.version>3.4.1</jquery.version>\n@@ -2157,7 +2157,7 @@ under the License.\n       <plugin>\n         <groupId>org.gaul</groupId>\n         <artifactId>modernizer-maven-plugin</artifactId>\n-        <version>1.9.0</version>\n+        <version>2.0.0</version>\n         <configuration>\n           <javaVersion>${targetJdk}</javaVersion>\n           <ignorePackages>"}]}