{"sha":"e2f36939957970ef39b822c611b65d17bfcec1ec","node_id":"MDY6Q29tbWl0NjM2ODc5MDYyOmUyZjM2OTM5OTU3OTcwZWYzOWI4MjJjNjExYjY1ZDE3YmZjZWMxZWM=","commit":{"author":{"name":"Francesco Chicchiriccò","email":"ilgrosso@apache.org","date":"2017-12-13T14:22:06Z"},"committer":{"name":"Francesco Chicchiriccò","email":"ilgrosso@apache.org","date":"2017-12-13T14:22:13Z"},"message":"Upgrading comomns-text","tree":{"sha":"26dc9f40e007abda406d8244b698ef274f3ecb2a","url":"https://api.github.com/repos/EnricoDAlessandro97UNI/syncope/git/trees/26dc9f40e007abda406d8244b698ef274f3ecb2a"},"url":"https://api.github.com/repos/EnricoDAlessandro97UNI/syncope/git/commits/e2f36939957970ef39b822c611b65d17bfcec1ec","comment_count":0,"verification":{"verified":false,"reason":"unsigned","signature":null,"payload":null}},"url":"https://api.github.com/repos/EnricoDAlessandro97UNI/syncope/commits/e2f36939957970ef39b822c611b65d17bfcec1ec","html_url":"https://github.com/EnricoDAlessandro97UNI/syncope/commit/e2f36939957970ef39b822c611b65d17bfcec1ec","comments_url":"https://api.github.com/repos/EnricoDAlessandro97UNI/syncope/commits/e2f36939957970ef39b822c611b65d17bfcec1ec/comments","author":{"login":"ilgrosso","id":1064664,"node_id":"MDQ6VXNlcjEwNjQ2NjQ=","avatar_url":"https://avatars.githubusercontent.com/u/1064664?v=4","gravatar_id":"","url":"https://api.github.com/users/ilgrosso","html_url":"https://github.com/ilgrosso","followers_url":"https://api.github.com/users/ilgrosso/followers","following_url":"https://api.github.com/users/ilgrosso/following{/other_user}","gists_url":"https://api.github.com/users/ilgrosso/gists{/gist_id}","starred_url":"https://api.github.com/users/ilgrosso/starred{/owner}{/repo}","subscriptions_url":"https://api.github.com/users/ilgrosso/subscriptions","organizations_url":"https://api.github.com/users/ilgrosso/orgs","repos_url":"https://api.github.com/users/ilgrosso/repos","events_url":"https://api.github.com/users/ilgrosso/events{/privacy}","received_events_url":"https://api.github.com/users/ilgrosso/received_events","type":"User","site_admin":false},"committer":{"login":"ilgrosso","id":1064664,"node_id":"MDQ6VXNlcjEwNjQ2NjQ=","avatar_url":"https://avatars.githubusercontent.com/u/1064664?v=4","gravatar_id":"","url":"https://api.github.com/users/ilgrosso","html_url":"https://github.com/ilgrosso","followers_url":"https://api.github.com/users/ilgrosso/followers","following_url":"https://api.github.com/users/ilgrosso/following{/other_user}","gists_url":"https://api.github.com/users/ilgrosso/gists{/gist_id}","starred_url":"https://api.github.com/users/ilgrosso/starred{/owner}{/repo}","subscriptions_url":"https://api.github.com/users/ilgrosso/subscriptions","organizations_url":"https://api.github.com/users/ilgrosso/orgs","repos_url":"https://api.github.com/users/ilgrosso/repos","events_url":"https://api.github.com/users/ilgrosso/events{/privacy}","received_events_url":"https://api.github.com/users/ilgrosso/received_events","type":"User","site_admin":false},"parents":[{"sha":"3df09968936118ce9a36ac438a8d0a6bf498990b","url":"https://api.github.com/repos/EnricoDAlessandro97UNI/syncope/commits/3df09968936118ce9a36ac438a8d0a6bf498990b","html_url":"https://github.com/EnricoDAlessandro97UNI/syncope/commit/3df09968936118ce9a36ac438a8d0a6bf498990b"}],"stats":{"total":2,"additions":1,"deletions":1},"files":[{"sha":"dd9672a94196abf22dc810b8db0c8929f020fb21","filename":"pom.xml","status":"modified","additions":1,"deletions":1,"changes":2,"blob_url":"https://github.com/EnricoDAlessandro97UNI/syncope/blob/e2f36939957970ef39b822c611b65d17bfcec1ec/pom.xml","raw_url":"https://github.com/EnricoDAlessandro97UNI/syncope/raw/e2f36939957970ef39b822c611b65d17bfcec1ec/pom.xml","contents_url":"https://api.github.com/repos/EnricoDAlessandro97UNI/syncope/contents/pom.xml?ref=e2f36939957970ef39b822c611b65d17bfcec1ec","patch":"@@ -400,7 +400,7 @@ under the License.\n     <commons-email.version>1.5</commons-email.version>\n     <commons-jexl.version>3.1</commons-jexl.version>\n     <commons-lang.version>3.7</commons-lang.version>\n-    <commons-text.version>1.1</commons-text.version>\n+    <commons-text.version>1.2</commons-text.version>\n     <commons-logging.version>1.1.3</commons-logging.version>\n \n     <joda.version>2.9.9</joda.version>"}]}