{"sha":"eecb7a11f1f2979731fbec0a75d8739975a92038","node_id":"MDY6Q29tbWl0NjM2ODc5MDYyOmVlY2I3YTExZjFmMjk3OTczMWZiZWMwYTc1ZDg3Mzk5NzVhOTIwMzg=","commit":{"author":{"name":"Francesco Chicchiriccò","email":"ilgrosso@apache.org","date":"2019-10-23T16:33:04Z"},"committer":{"name":"Francesco Chicchiriccò","email":"ilgrosso@apache.org","date":"2019-10-23T16:33:04Z"},"message":"Tweaking GitHub settings via .asf.yaml","tree":{"sha":"cdaafb8276b1c40ea69804ecea56ea612bced129","url":"https://api.github.com/repos/EnricoDAlessandro97UNI/syncope/git/trees/cdaafb8276b1c40ea69804ecea56ea612bced129"},"url":"https://api.github.com/repos/EnricoDAlessandro97UNI/syncope/git/commits/eecb7a11f1f2979731fbec0a75d8739975a92038","comment_count":0,"verification":{"verified":false,"reason":"unsigned","signature":null,"payload":null}},"url":"https://api.github.com/repos/EnricoDAlessandro97UNI/syncope/commits/eecb7a11f1f2979731fbec0a75d8739975a92038","html_url":"https://github.com/EnricoDAlessandro97UNI/syncope/commit/eecb7a11f1f2979731fbec0a75d8739975a92038","comments_url":"https://api.github.com/repos/EnricoDAlessandro97UNI/syncope/commits/eecb7a11f1f2979731fbec0a75d8739975a92038/comments","author":{"login":"ilgrosso","id":1064664,"node_id":"MDQ6VXNlcjEwNjQ2NjQ=","avatar_url":"https://avatars.githubusercontent.com/u/1064664?v=4","gravatar_id":"","url":"https://api.github.com/users/ilgrosso","html_url":"https://github.com/ilgrosso","followers_url":"https://api.github.com/users/ilgrosso/followers","following_url":"https://api.github.com/users/ilgrosso/following{/other_user}","gists_url":"https://api.github.com/users/ilgrosso/gists{/gist_id}","starred_url":"https://api.github.com/users/ilgrosso/starred{/owner}{/repo}","subscriptions_url":"https://api.github.com/users/ilgrosso/subscriptions","organizations_url":"https://api.github.com/users/ilgrosso/orgs","repos_url":"https://api.github.com/users/ilgrosso/repos","events_url":"https://api.github.com/users/ilgrosso/events{/privacy}","received_events_url":"https://api.github.com/users/ilgrosso/received_events","type":"User","site_admin":false},"committer":{"login":"ilgrosso","id":1064664,"node_id":"MDQ6VXNlcjEwNjQ2NjQ=","avatar_url":"https://avatars.githubusercontent.com/u/1064664?v=4","gravatar_id":"","url":"https://api.github.com/users/ilgrosso","html_url":"https://github.com/ilgrosso","followers_url":"https://api.github.com/users/ilgrosso/followers","following_url":"https://api.github.com/users/ilgrosso/following{/other_user}","gists_url":"https://api.github.com/users/ilgrosso/gists{/gist_id}","starred_url":"https://api.github.com/users/ilgrosso/starred{/owner}{/repo}","subscriptions_url":"https://api.github.com/users/ilgrosso/subscriptions","organizations_url":"https://api.github.com/users/ilgrosso/orgs","repos_url":"https://api.github.com/users/ilgrosso/repos","events_url":"https://api.github.com/users/ilgrosso/events{/privacy}","received_events_url":"https://api.github.com/users/ilgrosso/received_events","type":"User","site_admin":false},"parents":[{"sha":"885f25c459d0f53b5ebe623006cf3d4f4d076f28","url":"https://api.github.com/repos/EnricoDAlessandro97UNI/syncope/commits/885f25c459d0f53b5ebe623006cf3d4f4d076f28","html_url":"https://github.com/EnricoDAlessandro97UNI/syncope/commit/885f25c459d0f53b5ebe623006cf3d4f4d076f28"}],"stats":{"total":16,"additions":16,"deletions":0},"files":[{"sha":"9934f598c81c6b9085ee7aa7d6cd416e55ed03d7","filename":".asf.yaml","status":"added","additions":16,"deletions":0,"changes":16,"blob_url":"https://github.com/EnricoDAlessandro97UNI/syncope/blob/eecb7a11f1f2979731fbec0a75d8739975a92038/.asf.yaml","raw_url":"https://github.com/EnricoDAlessandro97UNI/syncope/raw/eecb7a11f1f2979731fbec0a75d8739975a92038/.asf.yaml","contents_url":"https://api.github.com/repos/EnricoDAlessandro97UNI/syncope/contents/.asf.yaml?ref=eecb7a11f1f2979731fbec0a75d8739975a92038","patch":"@@ -0,0 +1,16 @@\n+github:\n+  description: \"Apache Syncope\"\n+  homepage: https://syncope.apache.org/\n+  labels:\n+    - IAM\n+    - security\n+    - identity-management\n+    - identity-provisioning\n+    - identity-governance\n+  enabled_merge_buttons:\n+    # enable squash button:\n+    squash:  true\n+    # enable merge button:\n+    merge:   false\n+    # disable rebase button:\n+    rebase:  true"}]}